pvsystemprofiler/__init__.py
pvsystemprofiler/estimator.py
pvsystemprofiler/ground_truth_estimator.py
pvsystemprofiler/latitude_study.py
pvsystemprofiler/longitude_study.py
pvsystemprofiler/tilt_azimuth_study.py
pvsystemprofiler/algorithms/__init__.py
pvsystemprofiler/algorithms/optimized_sunrise_sunset.py
pvsystemprofiler/algorithms/performance_model_estimation.py
pvsystemprofiler/algorithms/angle_of_incidence/__init__.py
pvsystemprofiler/algorithms/angle_of_incidence/calculation.py
pvsystemprofiler/algorithms/angle_of_incidence/curve_fitting.py
pvsystemprofiler/algorithms/angle_of_incidence/dynamic_value_functions.py
pvsystemprofiler/algorithms/angle_of_incidence/lambda_functions.py
pvsystemprofiler/algorithms/latitude/__init__.py
pvsystemprofiler/algorithms/latitude/calculation.py
pvsystemprofiler/algorithms/latitude/estimation.py
pvsystemprofiler/algorithms/latitude/hours_daylight.py
pvsystemprofiler/algorithms/longitude/__init__.py
pvsystemprofiler/algorithms/longitude/calculation.py
pvsystemprofiler/algorithms/longitude/estimation.py
pvsystemprofiler/algorithms/longitude/fitting.py
pvsystemprofiler/algorithms/tilt_azimuth/__init__.py
pvsystemprofiler/algorithms/tilt_azimuth/daytime_threshold_quantile.py
pvsystemprofiler/scripts/__init__.py
pvsystemprofiler/scripts/parameter_estimation_script.py
pvsystemprofiler/scripts/run_partition_script.py
pvsystemprofiler/scripts/modules/__init__.py
pvsystemprofiler/scripts/modules/config_partitions.py
pvsystemprofiler/scripts/modules/create_partition.py
pvsystemprofiler/scripts/modules/local_partition_script.py
pvsystemprofiler/scripts/modules/script_functions.py
pvsystemprofiler/utilities/__init__.py
pvsystemprofiler/utilities/angle_of_incidence_function.py
pvsystemprofiler/utilities/declination_equation.py
pvsystemprofiler/utilities/equation_of_time.py
pvsystemprofiler/utilities/hour_angle_equation.py
pvsystemprofiler/utilities/progress.py
pvsystemprofiler/utilities/sunset_hour_angle_equation.py
solar_data_tools-2.0.0.dist-info/licenses/LICENSE
solar_data_tools-2.0.0.dist-info/METADATA
solar_data_tools-2.0.0.dist-info/WHEEL
solar_data_tools-2.0.0.dist-info/top_level.txt
solar_data_tools-2.0.0.dist-info/RECORD
