Metadata-Version: 2.4
Name: solar-data-tools
Version: 2.0.0
Summary: Tools for performing common tasks on solar PV data signals
Author-email: Bennet Meyers <bennetm@stanford.edu>
Maintainer-email: Sara Miskovich <smiskov@slac.stanford.edu>
License: BSD 2-Clause License
Project-URL: Homepage, https://github.com/slacgismo/solar-data-tools
Project-URL: Documentation, https://solar-data-tools.readthedocs.io/
Project-URL: Bug Tracker, https://github.com/slacgismo/solar-data-tools/issues
Project-URL: Discussions, https://github.com/slacgismo/solar-data-tools/discussions
Keywords: solar,pv,photovoltaic
Classifier: Development Status :: 4 - Beta
Classifier: License :: OSI Approved :: BSD License
Classifier: Programming Language :: Python :: 3 :: Only
Classifier: Programming Language :: Python :: 3.10
Classifier: Programming Language :: Python :: 3.11
Classifier: Programming Language :: Python :: 3.12
Classifier: Programming Language :: Python :: 3.13
Classifier: Intended Audience :: Science/Research
Classifier: Topic :: Scientific/Engineering
Requires-Python: >=3.10
License-File: LICENSE
Requires-Dist: scipy
Requires-Dist: numpy
Requires-Dist: pandas
Requires-Dist: scikit-learn
Requires-Dist: jupyter
Requires-Dist: matplotlib
Requires-Dist: seaborn
Requires-Dist: requests
Requires-Dist: pvlib
Requires-Dist: cvxpy
Requires-Dist: pykml
Requires-Dist: haversine
Requires-Dist: smart_open
Requires-Dist: sig-decomp
Requires-Dist: clarabel
Requires-Dist: qss
Requires-Dist: tqdm
Requires-Dist: spcqe
Provides-Extra: docs
Requires-Dist: sphinx; extra == "docs"
Requires-Dist: pydata-sphinx-theme; extra == "docs"
Requires-Dist: sphinx_design; extra == "docs"
Requires-Dist: nbsphinx; extra == "docs"
Requires-Dist: myst-parser; extra == "docs"
Requires-Dist: nbsphinx_link; extra == "docs"
Provides-Extra: mosek
Requires-Dist: mosek; extra == "mosek"
Provides-Extra: dask
Requires-Dist: numpy==2.0; extra == "dask"
Requires-Dist: dask==2024.5.2; extra == "dask"
Requires-Dist: distributed==2024.5.2; extra == "dask"
Requires-Dist: dask-cloudprovider[all]==2022.10.0; extra == "dask"
Requires-Dist: graphviz; extra == "dask"
Requires-Dist: bokeh; extra == "dask"
Dynamic: license-file
